Metadata-Version: 2.1
Name: novelpy
Version: 1.4
Summary: Calculate novelty indicators
Home-page: 
Author: Pelletier Pierre and Wirtz Kevin
Author-email: kevin.wirtz@unistra.fr
License: MIT
Keywords: Novelty,scientometrics
Classifier: Development Status :: 5 - Production/Stable
Classifier: Intended Audience :: Education
Classifier: Operating System :: Microsoft :: Windows :: Windows 10
Classifier: License :: OSI Approved :: MIT License
Classifier: Programming Language :: Python :: 3
License-File: LICENSE
Requires-Dist: spacy==3.7.2
Requires-Dist: pymongo==4.6.1
Requires-Dist: scikit-learn==1.4.0
Requires-Dist: glob2==0.7
Requires-Dist: networkx==3.2.1
Requires-Dist: python-louvain==0.16
Requires-Dist: pickle-mixin==1.0.2
Requires-Dist: pandas==2.1.4
Requires-Dist: multiprocess==0.70.16
Requires-Dist: pyyaml==6.0.1
Requires-Dist: wosfile==0.6
Requires-Dist: seaborn==0.13.2
